comuni_italiani/__init__.py
comuni_italiani/admin.py
comuni_italiani/apps.py
comuni_italiani/models.py
comuni_italiani/serializers.py
comuni_italiani/urls.py
comuni_italiani/views.py
comuni_italiani/management/commands/import_istat_data.py
comuni_italiani/migrations/0001_initial.py
comuni_italiani/migrations/0002_remove_comune_auto_code_provincia_auto_code.py
comuni_italiani/migrations/0003_alter_comune_options_alter_provincia_options_and_more.py
comuni_italiani/migrations/0004_comune_geographic_partition.py
comuni_italiani/migrations/0005_remove_comune_created_at_remove_comune_created_by_and_more.py
comuni_italiani/migrations/__init__.py
comuni_italiani/tests/__init__.py
comuni_italiani/tests/settings.py
comuni_italiani/tests/regioni/__init__.py
comuni_italiani/tests/regioni/fixtures.py
comuni_italiani/tests/regioni/test_regioni_models.py
comuni_italiani/utils/dynamic_field_serializers.py
comuni_italiani/utils/italian_localization.py
django_istat_localization-0.2.7.2.dist-info/LICENSE
django_istat_localization-0.2.7.2.dist-info/METADATA
django_istat_localization-0.2.7.2.dist-info/WHEEL
django_istat_localization-0.2.7.2.dist-info/top_level.txt
django_istat_localization-0.2.7.2.dist-info/RECORD
