Metadata-Version: 2.1
Name: django-istat-localization
Version: 0.2.7.2
Summary: A Django app to add ISTAT data resources Regions, Provinces and Cities from updated Official CSV file.
Home-page: https://github.com/FraCata00/django-istat-localization
Author: Francesco Cataldo
Author-email: francy111200@gmail.com
License: : OSI Approved :: BSD License
Requires-Python: >=3.8
License-File: LICENSE
Requires-Dist: Django >=4.0
